ticktack/__init__.py
ticktack/fitting.py
ticktack/model_builder.py
ticktack/resample.py
ticktack/ticktack.py
ticktack/data/Brehm21.hd5
ticktack/data/Buntgen18.hd5
ticktack/data/Guttler15.hd5
ticktack/data/Miyake17.hd5
ticktack/data/datasets/5259BCE/Brehm21_AlpineLarch.csv
ticktack/data/datasets/5259BCE/Brehm21_IrishOak.csv
ticktack/data/datasets/5259BCE/Brehm21_SibirianLarch.csv
ticktack/data/datasets/5259BCE/Brehm21_USABristlecone.csv
ticktack/data/datasets/5410BCE/Miyake21_Bristlecone.csv
ticktack/data/datasets/5410BCE/Miyake21_Finland1.csv
ticktack/data/datasets/5410BCE/Miyake21_Switzerland.csv
ticktack/data/datasets/660BCE-Ew/Sakurai20_CedarEw.csv
ticktack/data/datasets/660BCE-Lw/Sakurai20_CedarLw.csv
ticktack/data/datasets/7176BCE/Brehm21_AlpineLarch.csv
ticktack/data/datasets/7176BCE/Brehm21_GermanOak.csv
ticktack/data/datasets/7176BCE/Brehm21_USABristlecone.csv
ticktack/data/datasets/775AD-early-N/Büntgen18_ALT01.csv
ticktack/data/datasets/775AD-early-N/Büntgen18_AUT02.csv
ticktack/data/datasets/775AD-early-N/Büntgen18_CAN06.csv
ticktack/data/datasets/775AD-early-N/Büntgen18_GRE02.csv
ticktack/data/datasets/775AD-early-N/Büntgen18_MON09.csv
ticktack/data/datasets/775AD-early-N/Büntgen18_PAK04.csv
ticktack/data/datasets/775AD-early-N/Büntgen18_RUS15.csv
ticktack/data/datasets/775AD-early-N/Büntgen18_RUS17.csv
ticktack/data/datasets/775AD-early-N/Büntgen18_RUS20.csv
ticktack/data/datasets/775AD-early-N/Büntgen18_SWE02.csv
ticktack/data/datasets/775AD-early-N/Büntgen18_TIB01.csv
ticktack/data/datasets/775AD-early-S/Büntgen18_DAR01.csv
ticktack/data/datasets/775AD-early-S/Büntgen18_DAR06.csv
ticktack/data/datasets/775AD-early-S/Büntgen18_DAR07.csv
ticktack/data/datasets/775AD-early-S/Büntgen18_PAT02.csv
ticktack/data/datasets/775AD-early-S/Büntgen18_PAT03.csv
ticktack/data/datasets/775AD-early-S/Büntgen18_TAS01.csv
ticktack/data/datasets/775AD-late-N/Büntgen18_CHN01.csv
ticktack/data/datasets/775AD-late-N/Büntgen18_GER01.csv
ticktack-1.1.4.dist-info/LICENSE
ticktack-1.1.4.dist-info/METADATA
ticktack-1.1.4.dist-info/WHEEL
ticktack-1.1.4.dist-info/top_level.txt
ticktack-1.1.4.dist-info/RECORD
